bunnieinfra/__init__.py
bunnieinfra/jobs/__init__.py
bunnieinfra/jobs/bunnie_simulation.py
bunnieinfra/jobs/job_util.py
bunnieinfra/jobs/job_util_test.py
bunnieinfra-0.1.4.dist-info/METADATA
bunnieinfra-0.1.4.dist-info/WHEEL
bunnieinfra-0.1.4.dist-info/top_level.txt
bunnieinfra-0.1.4.dist-info/RECORD
