Metadata-Version: 2.1
Name: bunnieinfra
Version: 0.1.4
Summary: UNKNOWN
Home-page: UNKNOWN
Author: UNKNOWN
Author-email: UNKNOWN
License: UNKNOWN
Platform: UNKNOWN
Requires-Dist: bunnieshared (==0.1.7)
Requires-Dist: google-cloud-datastore (==1.7.3)
Requires-Dist: kubernetes (==9.0.0)
Requires-Dist: protobuf (==3.7.0)
